<?xml version="1.0" encoding="UTF-8"?>
<item><pubDate>Mon, 17 Apr 2017 00:33:28 +0200</pubDate><title><![CDATA[20170417003319]]></title><url><![CDATA[20170417003319]]></url><metad><![CDATA[]]></metad><menu><![CDATA[]]></menu><menuOrder><![CDATA[0]]></menuOrder><menuStatus><![CDATA[]]></menuStatus><template><![CDATA[template.php]]></template><parent><![CDATA[]]></parent><content><![CDATA[]]></content><private><![CDATA[]]></private><author><![CDATA[administrador]]></author><meta><![CDATA[_special_imovel]]></meta><special>imovel</special><codigo><![CDATA[20170417003319]]></codigo><finalidade><![CDATA[Locação]]></finalidade><tipo><![CDATA[Comércio Barracão]]></tipo><preco><![CDATA[20170417003319]]></preco><creDate>Mon, 17 Apr 2017 00:33:28 +0200</creDate><user><![CDATA[administrador]]></user></item>
